Workbook

Sheet Janvier
A1: Date | B1: Catégorie | C1: Description | D1: Recettes (+) | E1: Dépenses (-) | F1: Solde
A2: TOTAUX DU MOIS | D2: =SUM(D3:D5000) | E2: =SUM(E3:E5000) | F2: =D2-E2
A3: 46026.958 | B3: Salaire | C3: Virement | D3: 2500 | F3: =D3-E3
A4: 46028.958 | B4: Loyer | C4: Janvier | E4: 800 | F4: =F3+D4-E4

Sheet Février
A1: Date | B1: Catégorie | C1: Description | D1: Recettes (+) | E1: Dépenses (-) | F1: Solde
A2: TOTAUX DU MOIS | D2: =SUM(D3:D5000) | E2: =SUM(E3:E5000) | F2: =D2-E2

Sheet Mars
A1: Date | B1: Catégorie | C1: Description | D1: Recettes (+) | E1: Dépenses (-) | F1: Solde
A2: TOTAUX DU MOIS | D2: =SUM(D3:D5000) | E2: =SUM(E3:E5000) | F2: =D2-E2

Sheet Avril
A1: Date | B1: Catégorie | C1: Description | D1: Recettes (+) | E1: Dépenses (-) | F1: Solde
A2: TOTAUX DU MOIS | D2: =SUM(D3:D5000) | E2: =SUM(E3:E5000) | F2: =D2-E2

Sheet Mai
A1: Date | B1: Catégorie | C1: Description | D1: Recettes (+) | E1: Dépenses (-) | F1: Solde
A2: TOTAUX DU MOIS | D2: =SUM(D3:D5000) | E2: =SUM(E3:E5000) | F2: =D2-E2

Sheet Juin
A1: Date | B1: Catégorie | C1: Description | D1: Recettes (+) | E1: Dépenses (-) | F1: Solde
A2: TOTAUX DU MOIS | D2: =SUM(D3:D5000) | E2: =SUM(E3:E5000) | F2: =D2-E2

Sheet Juillet
A1: Date | B1: Catégorie | C1: Description | D1: Recettes (+) | E1: Dépenses (-) | F1: Solde
A2: TOTAUX DU MOIS | D2: =SUM(D3:D5000) | E2: =SUM(E3:E5000) | F2: =D2-E2

Sheet Août
A1: Date | B1: Catégorie | C1: Description | D1: Recettes (+) | E1: Dépenses (-) | F1: Solde
A2: TOTAUX DU MOIS | D2: =SUM(D3:D5000) | E2: =SUM(E3:E5000) | F2: =D2-E2

Sheet Septembre
A1: Date | B1: Catégorie | C1: Description | D1: Recettes (+) | E1: Dépenses (-) | F1: Solde
A2: TOTAUX DU MOIS | D2: =SUM(D3:D5000) | E2: =SUM(E3:E5000) | F2: =D2-E2

Sheet Octobre
A1: Date | B1: Catégorie | C1: Description | D1: Recettes (+) | E1: Dépenses (-) | F1: Solde
A2: TOTAUX DU MOIS | D2: =SUM(D3:D5000) | E2: =SUM(E3:E5000) | F2: =D2-E2

Sheet Novembre
A1: Date | B1: Catégorie | C1: Description | D1: Recettes (+) | E1: Dépenses (-) | F1: Solde
A2: TOTAUX DU MOIS | D2: =SUM(D3:D5000) | E2: =SUM(E3:E5000) | F2: =D2-E2

Sheet Décembre
A1: Date | B1: Catégorie | C1: Description | D1: Recettes (+) | E1: Dépenses (-) | F1: Solde
A2: TOTAUX DU MOIS | D2: =SUM(D3:D5000) | E2: =SUM(E3:E5000) | F2: =D2-E2

Sheet Synthèse Annuelle 2026
A1: Mois | B1: Total Recettes | C1: Total Dépenses | D1: Epargne (Solde)
A2: Janvier | B2: ='Janvier'!D2 | C2: ='Janvier'!E2 | D2: =B2-C2
A3: Février | B3: ='Février'!D2 | C3: ='Février'!E2 | D3: =B3-C3
A4: Mars | B4: ='Mars'!D2 | C4: ='Mars'!E2 | D4: =B4-C4
A5: Avril | B5: ='Avril'!D2 | C5: ='Avril'!E2 | D5: =B5-C5
A6: Mai | B6: ='Mai'!D2 | C6: ='Mai'!E2 | D6: =B6-C6
A7: Juin | B7: ='Juin'!D2 | C7: ='Juin'!E2 | D7: =B7-C7
A8: Juillet | B8: ='Juillet'!D2 | C8: ='Juillet'!E2 | D8: =B8-C8
A9: Août | B9: ='Août'!D2 | C9: ='Août'!E2 | D9: =B9-C9
A10: Septembre | B10: ='Septembre'!D2 | C10: ='Septembre'!E2 | D10: =B10-C10
A11: Octobre | B11: ='Octobre'!D2 | C11: ='Octobre'!E2 | D11: =B11-C11
A12: Novembre | B12: ='Novembre'!D2 | C12: ='Novembre'!E2 | D12: =B12-C12
A13: Décembre | B13: ='Décembre'!D2 | C13: ='Décembre'!E2 | D13: =B13-C13
A14: TOTAL ANNUEL | B14: =SUM(B2:B13) | C14: =SUM(C2:C13) | D14: =SUM(D2:D13)
